slapp/__init__.py
slapp/commands.py
slapp/config.py
slapp/constants.py
slapp/main.py
slapp/utils.py
slapp/version.py
slapp-0.5.1.dist-info/entry_points.txt
slapp-0.5.1.dist-info/LICENSE
slapp-0.5.1.dist-info/WHEEL
slapp-0.5.1.dist-info/METADATA
slapp-0.5.1.dist-info/RECORD
